oddoreven003/__init__.py
oddoreven003/core.py
oddoreven003-1.0.0.dist-info/licenses/LICENSE
oddoreven003-1.0.0.dist-info/METADATA
oddoreven003-1.0.0.dist-info/WHEEL
oddoreven003-1.0.0.dist-info/top_level.txt
oddoreven003-1.0.0.dist-info/RECORD
