Metadata-Version: 2.4
Name: oddoreven003
Version: 1.0.0
Summary: A tiny library to check if a number is odd or even.
Author-email: Your Name <your-email@example.com>
License: MIT License
Project-URL: Homepage, https://pypi.org/project/oddoreven16/
Project-URL: Source, https://github.com/yourusername/oddoreven16
Requires-Python: >=3.7
License-File: LICENSE
Dynamic: license-file
